{
  "version": 1,
  "author": "auto-generator",
  "parts": [
    {
      "type": "wokwi-text",
      "id": "title",
      "top": -60,
      "left": 300,
      "attrs": { "text": "SMART OFFICE – ROOM CONTROLLER" }
    },
    {
      "type": "wokwi-esp32-devkit-v1",
      "id": "esp32",
      "top": 150,
      "left": 0,
      "attrs": { "env": "micro", "nickname": "Gateway" }
    },
    {
      "type": "wokwi-text",
      "id": "gpio_contract",
      "top": 500,
      "left": 0,
      "attrs": {
        "text": "GPIO MAP:\nRelays:  2,4,5,12,13\nInd.Sw:  27,26,25,33,32\nMaster:  15   PIR: 14\nLEDs:    GPIO->220R->LED->GND"
      }
    },

    { "type": "wokwi-relay-module",  "id": "relay_light1", "top": 0,   "left": 300, "attrs": {} },
    { "type": "wokwi-text",          "id": "txt_light1",   "top": 10,  "left": 420, "attrs": { "text": "LIGHT 1\n(GPIO 2)" } },
    { "type": "wokwi-slide-switch",  "id": "sw_light1",    "top": 30,  "left": 510, "attrs": {} },
    { "type": "wokwi-text",          "id": "lbl_sw_l1",    "top": 10,  "left": 565, "attrs": { "text": "SW-L1\nGPIO27" } },
    { "type": "wokwi-resistor",      "id": "r_light1",     "top": 20,  "left": 650, "attrs": { "value": "220", "rotate": "90" } },
    { "type": "wokwi-led",           "id": "led_light1",   "top": 10,  "left": 700, "attrs": { "color": "yellow", "label": "LIGHT 1" } },

    { "type": "wokwi-relay-module",  "id": "relay_light2", "top": 120, "left": 300, "attrs": {} },
    { "type": "wokwi-text",          "id": "txt_light2",   "top": 130, "left": 420, "attrs": { "text": "LIGHT 2\n(GPIO 4)" } },
    { "type": "wokwi-slide-switch",  "id": "sw_light2",    "top": 150, "left": 510, "attrs": {} },
    { "type": "wokwi-text",          "id": "lbl_sw_l2",    "top": 130, "left": 565, "attrs": { "text": "SW-L2\nGPIO26" } },
    { "type": "wokwi-resistor",      "id": "r_light2",     "top": 140, "left": 650, "attrs": { "value": "220", "rotate": "90" } },
    { "type": "wokwi-led",           "id": "led_light2",   "top": 130, "left": 700, "attrs": { "color": "yellow", "label": "LIGHT 2" } },

    { "type": "wokwi-relay-module",  "id": "relay_light3", "top": 240, "left": 300, "attrs": {} },
    { "type": "wokwi-text",          "id": "txt_light3",   "top": 250, "left": 420, "attrs": { "text": "LIGHT 3\n(GPIO 5)" } },
    { "type": "wokwi-slide-switch",  "id": "sw_light3",    "top": 270, "left": 510, "attrs": {} },
    { "type": "wokwi-text",          "id": "lbl_sw_l3",    "top": 250, "left": 565, "attrs": { "text": "SW-L3\nGPIO25" } },
    { "type": "wokwi-resistor",      "id": "r_light3",     "top": 260, "left": 650, "attrs": { "value": "220", "rotate": "90" } },
    { "type": "wokwi-led",           "id": "led_light3",   "top": 250, "left": 700, "attrs": { "color": "yellow", "label": "LIGHT 3" } },

    { "type": "wokwi-relay-module",  "id": "relay_fan1",   "top": 360, "left": 300, "attrs": {} },
    { "type": "wokwi-text",          "id": "txt_fan1",     "top": 370, "left": 420, "attrs": { "text": "FAN 1\n(GPIO 12)" } },
    { "type": "wokwi-slide-switch",  "id": "sw_fan1",      "top": 390, "left": 510, "attrs": {} },
    { "type": "wokwi-text",          "id": "lbl_sw_f1",    "top": 370, "left": 565, "attrs": { "text": "SW-F1\nGPIO33" } },
    { "type": "wokwi-resistor",      "id": "r_fan1",       "top": 380, "left": 650, "attrs": { "value": "220", "rotate": "90" } },
    { "type": "wokwi-led",           "id": "led_fan1",     "top": 370, "left": 700, "attrs": { "color": "blue", "label": "FAN 1" } },

    { "type": "wokwi-relay-module",  "id": "relay_fan2",   "top": 480, "left": 300, "attrs": {} },
    { "type": "wokwi-text",          "id": "txt_fan2",     "top": 490, "left": 420, "attrs": { "text": "FAN 2\n(GPIO 13)" } },
    { "type": "wokwi-slide-switch",  "id": "sw_fan2",      "top": 510, "left": 510, "attrs": {} },
    { "type": "wokwi-text",          "id": "lbl_sw_f2",    "top": 490, "left": 565, "attrs": { "text": "SW-F2\nGPIO32" } },
    { "type": "wokwi-resistor",      "id": "r_fan2",       "top": 500, "left": 650, "attrs": { "value": "220", "rotate": "90" } },
    { "type": "wokwi-led",           "id": "led_fan2",     "top": 490, "left": 700, "attrs": { "color": "blue", "label": "FAN 2" } },

    { "type": "wokwi-slide-switch",  "id": "master_switch","top": 630, "left": 300, "attrs": {} },
    { "type": "wokwi-text",          "id": "txt_master",   "top": 640, "left": 400, "attrs": { "text": "MASTER ON/OFF (GPIO 15)" } },

    { "type": "wokwi-pir-motion-sensor", "id": "pir1",    "top": -50, "left": 0,   "attrs": {} }
  ],
  "connections": [
    ["esp32:D2",    "relay_light1:IN",  "green"],
    ["esp32:3V3",   "relay_light1:VCC", "red"],
    ["esp32:GND.1", "relay_light1:GND", "black"],
    ["esp32:D27",   "sw_light1:2",      "blue"],
    ["esp32:GND.2", "sw_light1:1",      "black"],
    ["esp32:D2",    "r_light1:1",       "yellow"],
    ["r_light1:2",  "led_light1:A",     "yellow"],
    ["led_light1:K","esp32:GND.1",      "black"],

    ["esp32:D4",    "relay_light2:IN",  "green"],
    ["esp32:3V3",   "relay_light2:VCC", "red"],
    ["esp32:GND.1", "relay_light2:GND", "black"],
    ["esp32:D26",   "sw_light2:2",      "blue"],
    ["esp32:GND.2", "sw_light2:1",      "black"],
    ["esp32:D4",    "r_light2:1",       "yellow"],
    ["r_light2:2",  "led_light2:A",     "yellow"],
    ["led_light2:K","esp32:GND.1",      "black"],

    ["esp32:D5",    "relay_light3:IN",  "green"],
    ["esp32:3V3",   "relay_light3:VCC", "red"],
    ["esp32:GND.1", "relay_light3:GND", "black"],
    ["esp32:D25",   "sw_light3:2",      "blue"],
    ["esp32:GND.2", "sw_light3:1",      "black"],
    ["esp32:D5",    "r_light3:1",       "yellow"],
    ["r_light3:2",  "led_light3:A",     "yellow"],
    ["led_light3:K","esp32:GND.1",      "black"],

    ["esp32:D12",   "relay_fan1:IN",    "green"],
    ["esp32:3V3",   "relay_fan1:VCC",   "red"],
    ["esp32:GND.1", "relay_fan1:GND",   "black"],
    ["esp32:D33",   "sw_fan1:2",        "blue"],
    ["esp32:GND.2", "sw_fan1:1",        "black"],
    ["esp32:D12",   "r_fan1:1",         "cyan"],
    ["r_fan1:2",    "led_fan1:A",       "cyan"],
    ["led_fan1:K",  "esp32:GND.1",      "black"],

    ["esp32:D13",   "relay_fan2:IN",    "green"],
    ["esp32:3V3",   "relay_fan2:VCC",   "red"],
    ["esp32:GND.1", "relay_fan2:GND",   "black"],
    ["esp32:D32",   "sw_fan2:2",        "blue"],
    ["esp32:GND.2", "sw_fan2:1",        "black"],
    ["esp32:D13",   "r_fan2:1",         "cyan"],
    ["r_fan2:2",    "led_fan2:A",       "cyan"],
    ["led_fan2:K",  "esp32:GND.1",      "black"],

    ["esp32:D15",   "master_switch:2",  "orange"],
    ["esp32:GND.2", "master_switch:1",  "black"],

    ["esp32:D14",   "pir1:OUT",         "green"],
    ["esp32:3V3",   "pir1:VCC",         "red"],
    ["esp32:GND.2", "pir1:GND",         "black"]
  ]
}